azureml/__init__.py
azureml/opendatasets/__init__.py
azureml/opendatasets/_open_image.py
azureml/opendatasets/environ.py
azureml/opendatasets/_utils/__init__.py
azureml/opendatasets/_utils/image_annotation_table_loader.py
azureml/opendatasets/_utils/image_common_types.py
azureml/opendatasets/_utils/image_downloader.py
azureml/opendatasets/_utils/image_selector.py
azureml/opendatasets/_utils/telemetry_utils.py
azureml/opendatasets/dataaccess/__init__.py
azureml/opendatasets/dataaccess/_open_image_blob_info.py
testOpendataset-1.4.dist-info/METADATA
testOpendataset-1.4.dist-info/WHEEL
testOpendataset-1.4.dist-info/license.txt
testOpendataset-1.4.dist-info/top_level.txt
testOpendataset-1.4.dist-info/RECORD
