Metadata-Version: 2.1
Name: testOpendataset
Version: 1.4
Summary: SDK for the Open Image Dataset.
Home-page: https://dev.azure.com/zhenwan/zhenwan_default/_git/AMLProjects
Author: zhenwan,t-tozho,t-zhiwan
Author-email: zhenwan@microsoft.com,t-tozho@microsoft.com,t-zhiwan@microsoft.com
License: UNKNOWN
Platform: UNKNOWN
Classifier: Programming Language :: Python :: 3
Classifier: License :: OSI Approved :: MIT License
Classifier: Operating System :: OS Independent
Requires-Dist: azureml-telemetry
Requires-Dist: azure-storage-blob
Requires-Dist: multimethods (>=1.0.0)
Requires-Dist: matplotlib (>=3.0.3)
Requires-Dist: opencv-contrib-python (>=4.0.25)
